nion/device_kit/CameraDevice.py
nion/device_kit/InstrumentDevice.py
nion/device_kit/ScanDevice.py
nion/device_kit/__init__.py
nion/device_kit/py.typed
nion/instrumentation/Acquisition.py
nion/instrumentation/AcquisitionController.py
nion/instrumentation/AcquisitionLibrary.py
nion/instrumentation/AcquisitionPreferences.py
nion/instrumentation/DataChannel.py
nion/instrumentation/DriftTracker.py
nion/instrumentation/HardwareSource.py
nion/instrumentation/ListListener.py
nion/instrumentation/MultiAcquire.py
nion/instrumentation/__init__.py
nion/instrumentation/camera_base.py
nion/instrumentation/py.typed
nion/instrumentation/scan_base.py
nion/instrumentation/stem_controller.py
nion/instrumentation/video_base.py
nion/instrumentation/test/AcquisitionController_test.py
nion/instrumentation/test/AcquisitionPanel_test.py
nion/instrumentation/test/AcquisitionTestContext.py
nion/instrumentation/test/AcquisitionTestContextConfiguration.py
nion/instrumentation/test/Acquisition_test.py
nion/instrumentation/test/CameraControl_test.py
nion/instrumentation/test/HardwareSource_test.py
nion/instrumentation/test/MultiAcquire_test.py
nion/instrumentation/test/MultipleShiftEELSAcquire_test.py
nion/instrumentation/test/ScanControl_test.py
nion/instrumentation/test/SynchronizedAcquisition_test.py
nion/instrumentation/test/__init__.py
nionswift_instrumentation-23.6.2.dist-info/licenses/LICENSE
nionswift_plugin/nion_instrumentation_ui/AcquisitionPanel.py
nionswift_plugin/nion_instrumentation_ui/AcquisitionRecorder.py
nionswift_plugin/nion_instrumentation_ui/CameraControlPanel.py
nionswift_plugin/nion_instrumentation_ui/HardwareSourceActions.py
nionswift_plugin/nion_instrumentation_ui/HardwareSourceChoice.py
nionswift_plugin/nion_instrumentation_ui/MultiAcquirePanel.py
nionswift_plugin/nion_instrumentation_ui/MultipleShiftEELSAcquire.py
nionswift_plugin/nion_instrumentation_ui/ScanAcquisition.py
nionswift_plugin/nion_instrumentation_ui/ScanControlPanel.py
nionswift_plugin/nion_instrumentation_ui/VideoControlPanel.py
nionswift_instrumentation-23.6.2.dist-info/METADATA
nionswift_instrumentation-23.6.2.dist-info/WHEEL
nionswift_instrumentation-23.6.2.dist-info/top_level.txt
nionswift_instrumentation-23.6.2.dist-info/RECORD
