Metadata-Version: 2.4
Name: nionswift-instrumentation
Version: 23.6.2
Summary: A Nion Swift library for STEM instrumentation (Camera, Scan, Video, Microscope).
Home-page: https://github.com/nion-software/nionswift-instrumentation-kit
Author: Nion Software
Author-email: swift@nion.com
License: GPL-3.0-only
Classifier: Development Status :: 5 - Production/Stable
Classifier: License :: OSI Approved :: GNU General Public License v3 (GPLv3)
Classifier: Programming Language :: Python :: 3.11
Classifier: Programming Language :: Python :: 3.12
Classifier: Programming Language :: Python :: 3.13
Requires-Python: >=3.11
License-File: LICENSE
Requires-Dist: niondata<16.0,>=15.9
Requires-Dist: nionswift<17.0,>=16.16
Requires-Dist: nionui<11.0,>=10.2
Requires-Dist: nionutils<5.0,>=4.14
Requires-Dist: numpy<3.0,>=2.0
Dynamic: license-file
